CHANGELOG.rst
MANIFEST.in
README.rst
setup.cfg
setup.py
LogWatcher.egg-info/PKG-INFO
LogWatcher.egg-info/SOURCES.txt
LogWatcher.egg-info/dependency_links.txt
LogWatcher.egg-info/not-zip-safe
LogWatcher.egg-info/top_level.txt
logwatcher/__init__.py
logwatcher/gmetriclib.py
logwatcher/graphitelib.py
logwatcher/logwatcher.py