Metadata-Version: 1.1
Name: LogWatcher
Version: 1.0
Summary: LogWatcher Daemon
Home-page: UNKNOWN
Author: Wil Heitritter
Author-email: no-reply@noreply.com
License: Apache
Keywords: Logs Metrics Access Apache Ganglia Graphite devops
Platform: UNKNOWN
Classifier: Programming Language :: Python
Classifier: Programming Language :: Python :: 2.7
Classifier: Intended Audience :: System Administrators 
